nhanes_data/__init__.py
nhanes_data/nhanes_data_api.py
tests/__init__.py
tests/test_nhanes_data_api.py
nhanes_pytool_api-0.1.1.dist-info/LICENSE.txt
nhanes_pytool_api-0.1.1.dist-info/METADATA
nhanes_pytool_api-0.1.1.dist-info/WHEEL
nhanes_pytool_api-0.1.1.dist-info/top_level.txt
nhanes_pytool_api-0.1.1.dist-info/RECORD
