Metadata-Version: 2.1
Name: nhanes-pytool-api
Version: 0.1.1
Summary: A tool for programmatic access to NHANES downloadable datasets
Home-page: https://github.com/kkrusere/NHANES-pyTOOL-API
Author: Kuzi Rusere
Author-email: kkrusere@gmail.com
Project-URL: Documentation, https://kkrusere.github.io/NHANES-pyTOOL-API/
Project-URL: Bug Tracker, https://github.com/kkrusere/NHANES-pyTOOL-API/issues
Classifier: Development Status :: 4 - Beta
Classifier: License :: OSI Approved :: MIT License
Classifier: Programming Language :: Python :: 3.8
Classifier: Operating System :: OS Independent
Classifier: Topic :: Software Development :: Libraries :: Python Modules
Classifier: Topic :: Scientific/Engineering :: Information Analysis
Requires-Python: >=3.8
License-File: LICENSE.txt
Requires-Dist: numpy
Requires-Dist: pandas
Provides-Extra: test
Requires-Dist: pytest ; extra == 'test'
